aether_sphinx/__init__.py
aether_sphinx/breadcrumbs.html
aether_sphinx/content.html
aether_sphinx/footer.html
aether_sphinx/layout.html
aether_sphinx/search.html
aether_sphinx/searchbox.html
aether_sphinx/sidebar.html
aether_sphinx/theme.conf
aether_sphinx/versions.html
aether_sphinx/locale/sphinx.pot
aether_sphinx/locale/en/LC_MESSAGES/sphinx.mo
aether_sphinx/locale/en/LC_MESSAGES/sphinx.po
aether_sphinx/locale/es/LC_MESSAGES/sphinx.mo
aether_sphinx/locale/es/LC_MESSAGES/sphinx.po
aether_sphinx/locale/nl/LC_MESSAGES/sphinx.mo
aether_sphinx/locale/nl/LC_MESSAGES/sphinx.po
aether_sphinx/locale/ru/LC_MESSAGES/sphinx.mo
aether_sphinx/locale/ru/LC_MESSAGES/sphinx.po
aether_sphinx/static/css/badge_only.css
aether_sphinx/static/css/edit-find-dark.svg
aether_sphinx/static/css/edit-find.svg
aether_sphinx/static/css/go-next.svg
aether_sphinx/static/css/icons.eot
aether_sphinx/static/css/icons.svg
aether_sphinx/static/css/icons.ttf
aether_sphinx/static/css/icons.woff
aether_sphinx/static/css/icons.woff2
aether_sphinx/static/css/theme.css
aether_sphinx/static/css/fonts/Roboto-Slab-Bold.woff
aether_sphinx/static/css/fonts/Roboto-Slab-Bold.woff2
aether_sphinx/static/css/fonts/Roboto-Slab-Regular.woff
aether_sphinx/static/css/fonts/Roboto-Slab-Regular.woff2
aether_sphinx/static/css/fonts/fontawesome-webfont.eot
aether_sphinx/static/css/fonts/fontawesome-webfont.svg
aether_sphinx/static/css/fonts/fontawesome-webfont.ttf
aether_sphinx/static/css/fonts/fontawesome-webfont.woff
aether_sphinx/static/css/fonts/fontawesome-webfont.woff2
aether_sphinx/static/css/fonts/lato-bold-italic.woff
aether_sphinx/static/css/fonts/lato-bold-italic.woff2
aether_sphinx/static/css/fonts/lato-bold.woff
aether_sphinx/static/css/fonts/lato-bold.woff2
aether_sphinx/static/css/fonts/lato-normal-italic.woff
aether_sphinx/static/css/fonts/lato-normal-italic.woff2
aether_sphinx/static/css/fonts/lato-normal.woff
aether_sphinx/static/css/fonts/lato-normal.woff2
aether_sphinx/static/js/badge_only.js
aether_sphinx-2.3.0.dist-info/LICENSE
aether_sphinx-2.3.0.dist-info/METADATA
aether_sphinx-2.3.0.dist-info/WHEEL
aether_sphinx-2.3.0.dist-info/entry_points.txt
aether_sphinx-2.3.0.dist-info/top_level.txt
aether_sphinx-2.3.0.dist-info/RECORD
